numerauto/__init__.py
numerauto/eventhandlers.py
numerauto/numerauto.py
numerauto/robust_numerapi.py
numerauto/utils.py
numerauto-0.3.1.dist-info/LICENSE
numerauto-0.3.1.dist-info/METADATA
numerauto-0.3.1.dist-info/WHEEL
numerauto-0.3.1.dist-info/top_level.txt
numerauto-0.3.1.dist-info/RECORD
