Metadata-Version: 2.1
Name: numerauto
Version: 0.3.1
Summary: Daemon to facilitate automatically competing in the Numerai machine learning competition
Home-page: https://github.com/thebrain85/numerauto
Maintainer: The Brain
Maintainer-email: thebrainz1985@gmail.com
License: GNU General Public License v3
Platform: OS Independent
Classifier: Development Status :: 3 - Alpha
Classifier: Environment :: Console
Classifier: Intended Audience :: Science/Research
Classifier: License :: OSI Approved :: GNU General Public License v3 (GPLv3)
Classifier: Operating System :: OS Independent
Classifier: Programming Language :: Python
Classifier: Programming Language :: Python :: 3
Classifier: Topic :: Scientific/Engineering
Requires-Python: >=3
Requires-Dist: requests
Requires-Dist: pytz
Requires-Dist: python-dateutil
Requires-Dist: pandas
Requires-Dist: numerapi
